openai_cli/__init__.py
openai_cli/cli.py
openai_cli/client.py
openai_cli/config.py
openai_cli/test_cli.py
openai_cli/test_client.py
openai_cli/test_config.py
openai_cli-1.0.0.dist-info/LICENSE
openai_cli-1.0.0.dist-info/METADATA
openai_cli-1.0.0.dist-info/WHEEL
openai_cli-1.0.0.dist-info/entry_points.txt
openai_cli-1.0.0.dist-info/top_level.txt
openai_cli-1.0.0.dist-info/RECORD
