Metadata-Version: 2.1
Name: openai-cli
Version: 1.0.0
Summary: Command-line client for OpenAI API
Home-page: https://github.com/peterdemin/openai-cli
Author: Peter Demin
Author-email: peterdemin@gmail.com
Classifier: Development Status :: 4 - Beta
Classifier: Intended Audience :: Developers
Classifier: License :: OSI Approved :: MIT License
Classifier: Programming Language :: Python :: 3
Classifier: Programming Language :: Python :: 3 :: Only
Requires-Python: >=3.12
License-File: LICENSE
Requires-Dist: requests
Requires-Dist: click
